monit/__init__.py
monit/config.py
monit/core.py
monit/database.py
monit/error.py
monit/func.py
monit/log2file.py
monit/logger.py
monit/verify_env.py
monit_agd-1.3.10.dist-info/LICENSE
monit_agd-1.3.10.dist-info/METADATA
monit_agd-1.3.10.dist-info/WHEEL
monit_agd-1.3.10.dist-info/top_level.txt
monit_agd-1.3.10.dist-info/RECORD
