Metadata-Version: 2.1
Name: monit-agd
Version: 1.3.10
Summary: Programa de monitoramento de código python, desenvolvido para ser utilizado pelas funcionário da Agência de dados
Home-page: https://github.com/arktnld/monit
Author: arktnld
Author-email: arktnld@gmail.com
License: MIT
Classifier: Development Status :: 3 - Alpha
Classifier: Programming Language :: Python :: 3
Classifier: License :: OSI Approved :: MIT License
Classifier: Operating System :: OS Independent
License-File: LICENSE
Requires-Dist: sqlalchemy
Requires-Dist: pymysql
Requires-Dist: psutil
Requires-Dist: python-dotenv
